odoo/addons/mrp_production_consumption_warning/README.rst
odoo/addons/mrp_production_consumption_warning/__init__.py
odoo/addons/mrp_production_consumption_warning/__manifest__.py
odoo/addons/mrp_production_consumption_warning/i18n/mrp_production_consumption_warning.pot
odoo/addons/mrp_production_consumption_warning/models/__init__.py
odoo/addons/mrp_production_consumption_warning/models/mrp_production.py
odoo/addons/mrp_production_consumption_warning/readme/CONTRIBUTORS.rst
odoo/addons/mrp_production_consumption_warning/readme/CREDITS.rst
odoo/addons/mrp_production_consumption_warning/readme/DESCRIPTION.rst
odoo/addons/mrp_production_consumption_warning/static/description/icon.png
odoo/addons/mrp_production_consumption_warning/static/description/index.html
odoo/addons/mrp_production_consumption_warning/tests/__init__.py
odoo/addons/mrp_production_consumption_warning/tests/test_consumption_warning.py
odoo/addons/mrp_production_consumption_warning/views/mrp_production_views.xml
odoo_addon_mrp_production_consumption_warning-15.0.1.0.0.2.dist-info/METADATA
odoo_addon_mrp_production_consumption_warning-15.0.1.0.0.2.dist-info/WHEEL
odoo_addon_mrp_production_consumption_warning-15.0.1.0.0.2.dist-info/top_level.txt
odoo_addon_mrp_production_consumption_warning-15.0.1.0.0.2.dist-info/RECORD
